{"equipments":[{"id":1,"name":"Caméra de surveillance","description":"Caméra IP de surveillance avec vision nocturne","status":"En fonctionnement","location":"Salle de contrôle","owner":"Acme"},{"id":2,"name":"Extincteur","description":"Extincteur à poudre de bicarbonate de sodium","status":"En panne","location":"Bureau d'Imene","owner":"BetaCorp"},{"id":3,"name":"Porte coupe-feu","description":"Porte coupe-feu en acier inoxydable","status":"En fonctionnement","location":"Salle de serveurs","owner":"Acme"},{"id":5,"name":"Contrôle d'accès","description":"Système de contrôle d'accès par carte RFID","status":"En panne","location":"Entrée principale","owner":"Acme"},{"id":6,"name":"Extincteur","description":"Extincteur à poudre pour les feux de classe A, B et C","status":"Hors service","location":"Cuisine","owner":"BetaCorp"},{"id":7,"name":"Alarme","description":"Système d'alarme sans fil ","status":"Hors service","location":"Bureau d'Imene","owner":"BetaCorp"},{"id":8,"name":"Contrôle oxygène","description":"Système de contrôle des taux d'oxygène","status":"En panne","location":"Entrée nord","owner":"BetaCorp"},{"id":9,"name":"Alarme anti-intrusion","description":"Système d'alarme sans fil avec capteurs de mouvement","status":"En panne","location":"Bureau du PDG","owner":"Acme"},{"id":10,"name":"Contrôle d'accès","description":"Système de contrôle d'accès par carte RFID","status":"En panne","location":"Entrée principale","owner":"Acme"},{"id":11,"name":"Système de contrôle d'accès","description":"Système de contrôle d'accès avec badges RFID","status":"En fonctionnement","location":"Hall d'entrée","owner":"Acme"},{"id":12,"name":"Ventilateur industriel","description":"Ventilateur industriel avec hélice en aluminium","status":"En fonctionnement","location":"Salle de production","owner":"BetaCorp"},{"id":13,"name":"Chauffage à gaz","description":"Chauffage à gaz avec thermostat","status":"Hors service","location":"Bureau 205","owner":"Acme"},{"id":14,"name":"Climatiseur","description":"Climatiseur avec télécommande","status":"En fonctionnement","location":"Bureau 301","owner":"BetaCorp"},{"id":15,"name":"Projecteur vidéo","description":"Projecteur vidéo HD avec entrée HDMI","status":"Hors service","location":"Entrée nord","owner":"BetaCorp"},{"id":16,"name":"Exemple","description":"exemple","status":"exemple","location":"exemple","owner":"imene"}],"entreprises":[{"id":1,"name":"Acme","username":"acmeuser","password":"acmepass"},{"id":2,"name":"BetaCorp","username":"betuser","password":"betpass"},{"id":3,"name":"amazon","username":"amazon","password":"ines"}]}